popcat_py/__init__.py
popcat_py/popcat.py
popcat_py-1.0.7.dist-info/AUTHORS.rst
popcat_py-1.0.7.dist-info/LICENSE.txt
popcat_py-1.0.7.dist-info/METADATA
popcat_py-1.0.7.dist-info/WHEEL
popcat_py-1.0.7.dist-info/entry_points.txt
popcat_py-1.0.7.dist-info/top_level.txt
popcat_py-1.0.7.dist-info/RECORD
